README.md
setup.py
metawiki/__init__.py
metawiki/fmap.py
metawiki/map.py
metawiki/test_fmap.py
metawiki/test_map.py
metawiki.egg-info/PKG-INFO
metawiki.egg-info/SOURCES.txt
metawiki.egg-info/dependency_links.txt
metawiki.egg-info/not-zip-safe
metawiki.egg-info/requires.txt
metawiki.egg-info/top_level.txt
metawiki/data/LOV.json
metawiki/data/__init__.py