Metadata-Version: 2.1
Name: metawiki
Version: 0.1.12
Summary: A simple map for urls of definitions in notable sources.
Home-page: https://github.com/wefindx/metawiki
Author: Mindey
Author-email: mindey@qq.com
License: AGPL
Platform: UNKNOWN
Provides-Extra: test
